Metadata-Version: 2.1
Name: Combinify
Version: 0.2.0
Summary: A combinatory package
Home-page: https://github.com/jgomezba/Combinify
Author: Your Name
Author-email: gomezbarrosojavier@example.com
Classifier: Programming Language :: Python :: 3
Classifier: License :: OSI Approved :: MIT License
Classifier: Operating System :: OS Independent
Requires-Python: >=3.6
